objective_thresholds/__init__.py
objective_thresholds/flood.py
objective_thresholds/lowflow.py
objective_thresholds-0.0.2.dist-info/LICENSE
objective_thresholds-0.0.2.dist-info/METADATA
objective_thresholds-0.0.2.dist-info/WHEEL
objective_thresholds-0.0.2.dist-info/top_level.txt
objective_thresholds-0.0.2.dist-info/RECORD
