Metadata-Version: 2.1
Name: objective-thresholds
Version: 0.0.2
Summary: Objective threshold level calculation based on a flow duration curve (FDC)
Home-page: https://github.com/chrisrac/objective_thresholds
Author: Krzysztof Raczynski
Author-email: chris.rac9@gmail.com
Project-URL: Bug Tracker, https://github.com/chrisrac/objective_thresholds/issues
Classifier: Programming Language :: Python :: 3
Classifier: License :: OSI Approved :: MIT License
Classifier: Operating System :: OS Independent
Requires-Python: >=3.4
License-File: LICENSE
Requires-Dist: pandas
Requires-Dist: numpy
Requires-Dist: jenkspy
